Metadata-Version: 2.4
Name: cudass
Version: 0.1.2
Summary: High-performance CUDA sparse linear solver
Author: Rui Yao
License: Apache-2.0
Project-URL: Homepage, https://github.com/MoCA-Technion/cudass
Project-URL: Repository, https://github.com/MoCA-Technion/cudass
Project-URL: Documentation, https://moca-technion.github.io/cudass/
Keywords: cuda,sparse,linear solver,pytorch,cudss,cusolver
Classifier: License :: OSI Approved :: Apache Software License
Classifier: Programming Language :: Python :: 3
Classifier: Programming Language :: Python :: 3.8
Classifier: Programming Language :: Python :: 3.9
Classifier: Programming Language :: Python :: 3.10
Classifier: Programming Language :: Python :: 3.11
Classifier: Programming Language :: Python :: 3.12
Classifier: Topic :: Scientific/Engineering :: Mathematics
Requires-Python: >=3.8
License-File: LICENSE
License-File: NOTICE
Requires-Dist: torch>=2.0
Requires-Dist: nvidia-cudss-cu12>=0.6
Provides-Extra: test
Requires-Dist: pytest>=7.0; extra == "test"
Requires-Dist: pytest-cov; extra == "test"
Provides-Extra: docs
Requires-Dist: sphinx>=5.0; extra == "docs"
Requires-Dist: furo; extra == "docs"
Provides-Extra: dev
Requires-Dist: ruff; extra == "dev"
Requires-Dist: darglint; extra == "dev"
Dynamic: license-file
